changelog.txt
raincoat_prowlarr/__init__.py
raincoat_prowlarr/config.py
raincoat_prowlarr/helpers.py
raincoat_prowlarr/raincoat_prowlarr.json
raincoat_prowlarr/raincoat_prowlarr.py
raincoat_prowlarr/shared.py
raincoat_prowlarr/torrent.py
raincoat_prowlarr-0.2.3.dist-info/entry_points.txt
raincoat_prowlarr-0.2.3.dist-info/WHEEL
raincoat_prowlarr-0.2.3.dist-info/METADATA
raincoat_prowlarr-0.2.3.dist-info/RECORD
