Metadata-Version: 2.1
Name: raincoat-prowlarr
Version: 0.2.3
Summary: Raincoat-prowlarr is a tool to search torrents using jackett and search torrents and nzb files using prowlarr/jackett/MovieInfo and send them to your client.
Home-page: https://github.com/crvideo/raincoat_prowlarr
License: MIT
Keywords: transmission,qbittorrent,deluge,jackett,torrent,nzbget,MovieInfo
Author: crvideoVR
Requires-Python: >=3.7,<4.0
Classifier: Development Status :: 4 - Beta
Classifier: License :: OSI Approved :: MIT License
Classifier: Operating System :: OS Independent
Classifier: Programming Language :: Python :: 3
Classifier: Programming Language :: Python :: 3 :: Only
Classifier: Programming Language :: Python :: 3.10
Classifier: Programming Language :: Python :: 3.7
Classifier: Programming Language :: Python :: 3.8
Classifier: Programming Language :: Python :: 3.9
Requires-Dist: colorama (>=0.4.3,<0.5.0)
Requires-Dist: deluge-client (>=1.8.0,<2.0.0)
Requires-Dist: getmovieinfo (>=0.1.5,<0.2.0)
Requires-Dist: justlog (>=0.1.1.5,<0.2.0.0)
Requires-Dist: python-qbittorrent (>=0.4.2,<0.5.0)
Requires-Dist: requests (>=2.23.0,<3.0.0)
Requires-Dist: tabulate (>=0.8.7,<0.9.0)
Requires-Dist: transmission-clutch (>=6.0.2,<7.0.0)
Project-URL: Repository, https://github.com/crvideo/raincoat_prowlarr
